pysh/pysh.py
python_pysh-0.0.2.dist-info/LICENSE
python_pysh-0.0.2.dist-info/METADATA
python_pysh-0.0.2.dist-info/WHEEL
python_pysh-0.0.2.dist-info/entry_points.txt
python_pysh-0.0.2.dist-info/top_level.txt
python_pysh-0.0.2.dist-info/RECORD
