Metadata-Version: 2.1
Name: python-pysh
Version: 0.0.2
Summary: A Python package that mimics the Oh-My-ZSH shell. This package creates a colorful ZSH prompt.
Home-page: https://github.com/Python3-8/python-pysh
Author: Pranav Balaji Pooruli
Author-email: pranav.pooruli@gmail.com
License: MIT
Platform: UNKNOWN
Classifier: License :: OSI Approved :: MIT License
Classifier: Programming Language :: Python :: 3
Classifier: Programming Language :: Python :: 3.8
